airt_utils/__init__.py
airt_utils/mlflow/__init__.py
airt_utils/mlflow/decorators.py
airt_utils/mlflow/helpers.py
airt_utils-0.1.7.dist-info/LICENSE
airt_utils-0.1.7.dist-info/METADATA
airt_utils-0.1.7.dist-info/WHEEL
airt_utils-0.1.7.dist-info/RECORD
