Metadata-Version: 2.1
Name: airt_utils
Version: 0.1.7
Summary: Utilities for experiment-centric AI Red Teaming workflows
License: MIT
Keywords: mlflow,logging,ai-red-team
Author: Joe Lucas
Author-email: joe@joetl.com
Requires-Python: >=3.10,<4.0
Classifier: License :: OSI Approved :: MIT License
Classifier: Programming Language :: Python
Classifier: Programming Language :: Python :: 3
Classifier: Programming Language :: Python :: 3.10
Classifier: Programming Language :: Python :: 3.11
Classifier: Programming Language :: Python :: 3.12
Classifier: Programming Language :: Python :: 3.7
Classifier: Programming Language :: Python :: 3.8
Classifier: Programming Language :: Python :: 3.9
Requires-Dist: mlflow (>=2.15.0,<3.0.0)
Requires-Dist: requests (>=2.32.3,<3.0.0)
